srwlpy.cpython-36m-darwin.so
vinyl_srw/SRWLIB_ExampleViewDataFile.py
vinyl_srw/__init__.py
vinyl_srw/srwl_bl.py
vinyl_srw/srwl_uti_cryst.py
vinyl_srw/srwl_uti_mag.py
vinyl_srw/srwl_uti_smp.py
vinyl_srw/srwl_uti_src.py
vinyl_srw/srwl_uti_und.py
vinyl_srw/srwlib.py
vinyl_srw/uti_io.py
vinyl_srw/uti_math.py
vinyl_srw/uti_parse.py
vinyl_srw/uti_plot.py
vinyl_srw/uti_plot_com.py
vinyl_srw/uti_plot_matplotlib.py
vinyl_srw/tests/__init__.py
vinyl_srw/tests/conftest.py
vinyl_srw/tests/test_examples.py
vinyl_srw-1.0.1.dist-info/AUTHORS.rst
vinyl_srw-1.0.1.dist-info/LICENSE
vinyl_srw-1.0.1.dist-info/METADATA
vinyl_srw-1.0.1.dist-info/WHEEL
vinyl_srw-1.0.1.dist-info/top_level.txt
vinyl_srw-1.0.1.dist-info/RECORD
