Metadata-Version: 2.1
Name: vinyl-srw
Version: 1.0.1
Summary: Synchrotron Radiation Workshop
Home-page: https://github.com/PaNOSC-ViNYL/srwpy
Author: European Synchrotron Radiation Facility
Author-email: thibault.vallois@esrf.fr
License: BSD (3-clause)
Platform: UNKNOWN
Classifier: Development Status :: 2 - Pre-Alpha
Classifier: Natural Language :: English
Classifier: Programming Language :: Python :: 2
Classifier: Programming Language :: Python :: 3
Classifier: Operating System :: POSIX :: Linux
Classifier: Operating System :: MacOS :: MacOS X
Classifier: Operating System :: Microsoft :: Windows
Requires-Dist: matplotlib
Requires-Dist: numpy
Requires-Dist: pillow
Requires-Dist: scipy
